evb/__init__.py
evb/errors.py
evb/evb.py
evb/responses.py
evb.py-1.1.1.dist-info/LICENSE
evb.py-1.1.1.dist-info/METADATA
evb.py-1.1.1.dist-info/WHEEL
evb.py-1.1.1.dist-info/top_level.txt
evb.py-1.1.1.dist-info/RECORD
