Metadata-Version: 2.1
Name: evb.py
Version: 1.1.1
Summary: Asynchronous wrapper for the EditVideoBot API
Home-page: https://github.com/regulad/evb.py
Author: regulad
Author-email: regulad@outlook.com
License: GPLv3
Download-URL: https://codeload.github.com/regulad/evb.py/zip/refs/heads/main
Keywords: async,api
Platform: UNKNOWN
Classifier: Intended Audience :: Developers
Classifier: License :: OSI Approved :: GNU General Public License v3 (GPLv3)
Classifier: Programming Language :: Python :: 3.7
Classifier: Programming Language :: Python :: 3.8
Classifier: Programming Language :: Python :: 3.9
Requires-Python: <4,>=3.7
License-File: LICENSE
Requires-Dist: aiohttp (<4,>=3.8.1)
Requires-Dist: typing-extensions (<5,>=4.0.1)
